soniox/__init__.py
soniox/client.py
soniox/exceptions.py
soniox/languages.py
soniox/py.typed
soniox/types.py
soniox_sdk-0.1.6.dist-info/licenses/LICENSE.txt
soniox_sdk-0.1.6.dist-info/METADATA
soniox_sdk-0.1.6.dist-info/WHEEL
soniox_sdk-0.1.6.dist-info/top_level.txt
soniox_sdk-0.1.6.dist-info/RECORD
