Metadata-Version: 2.4
Name: soniox-sdk
Version: 0.1.6
Summary: Python SDK for Soniox speech-to-text API
Author-email: Mahdi Kiani <mahdikiany@gmail.com>, Amir Shokouhiniya <Shokouhiniya@gmail.com>, Pishrun <dev@pish.run>
Maintainer-email: Mahdi Kiani <mahdikiany@gmail.com>, Amir Shokouhiniya <Shokouhiniya@gmail.com>, Pishrun <dev@pish.run>
License: Copyright (c) 2024 Mahdi Kiani
Project-URL: Homepage, https://github.com/mahdikiani/soniox
Project-URL: Bug Reports, https://github.com/mahdikiani/soniox/issues
Project-URL: Say Thanks!, https://saythanks.io/to/mahdikiani
Project-URL: Source, https://github.com/mahdikiani/soniox
Keywords: soniox,speech-to-text,api,sdk
Classifier: Development Status :: 5 - Production/Stable
Classifier: Intended Audience :: Developers
Classifier: Topic :: Software Development :: Build Tools
Classifier: License :: OSI Approved :: MIT License
Classifier: Programming Language :: Python :: 3
Classifier: Programming Language :: Python :: 3.10
Classifier: Programming Language :: Python :: 3.11
Classifier: Programming Language :: Python :: 3.12
Classifier: Programming Language :: Python :: 3 :: Only
Requires-Python: >=3.10
License-File: LICENSE.txt
Requires-Dist: httpx>=0.27.0
Requires-Dist: pydantic>=2.11.9
Requires-Dist: websockets>=12.0
Provides-Extra: dev
Requires-Dist: check-manifest; extra == "dev"
Requires-Dist: ruff; extra == "dev"
Requires-Dist: mypy; extra == "dev"
Provides-Extra: test
Requires-Dist: coverage; extra == "test"
Requires-Dist: pytest>=8.0.0; extra == "test"
Requires-Dist: pytest-asyncio>=0.23.0; extra == "test"
Requires-Dist: pytest-cov>=4.1.0; extra == "test"
Requires-Dist: pytest-httpx>=0.35.0; extra == "test"
Requires-Dist: pytest-mock>=3.12.0; extra == "test"
Requires-Dist: respx>=0.20.0; extra == "test"
Dynamic: license-file
